README.txt
setup.cfg
setup.py
docs/HISTORY.txt
twistedschedule/__init__.py
twistedschedule/cron.py
twistedschedule/interfaces.py
twistedschedule/task.py
twistedschedule.egg-info/PKG-INFO
twistedschedule.egg-info/SOURCES.txt
twistedschedule.egg-info/dependency_links.txt
twistedschedule.egg-info/not-zip-safe
twistedschedule.egg-info/requires.txt
twistedschedule.egg-info/top_level.txt
twistedschedule/test/__init__.py
twistedschedule/test/test_cron.py
twistedschedule/test/test_task.py