Metadata-Version: 1.0
Name: twistedschedule
Version: 1.0b1
Summary: A scheduling plugin for twisted
Home-page: http://code.google.com/p/twistedcronservice
Author: Benjamin Liles (Texas A&M University)
Author-email: bliles@library.tamu.edu
License: MIT
Keywords: twisted python scheduling cron
Platform: UNKNOWN
Classifier: Programming Language :: Python
Classifier: Topic :: Software Development :: Libraries :: Python Modules
Classifier: Framework :: Twisted
Classifier: Development Status :: 4 - Beta
Classifier: Intended Audience :: Developers
Classifier: License :: OSI Approved :: GNU General Public License (GPL)
Classifier: Topic :: Software Development :: Libraries :: Application Frameworks
Classifier: Topic :: Software Development :: Libraries :: Python Modules
